{
  "result": [
    {
      "status": 0,
      "user_id": 1,
      "user_name": "天天"
    },
    {
      "status": 1,
      "user_id": 2,
      "user_name": "啊啊"
    },
    {
      "status": 0,
      "user_id": 3,
      "user_name": "闭包"
    },
    {
      "status": 1,
      "user_id": 4,
      "user_name": "和融通"
    },
    {
      "status": 0,
      "user_id": 5,
      "user_name": "请问天"
    },
    {
      "status": 1,
      "user_id": 6,
      "user_name": "无药可救"
    },
    {
      "status": 1,
      "user_id": 7,
      "user_name": "结合"
    },
    {
      "status": 0,
      "user_id": 8,
      "user_name": "执行"
    },
    {
      "status": 0,
      "user_id": 9,
      "user_name": "难进"
    },
    {
      "status": 0,
      "user_id": 10,
      "user_name": "鸡个"
    },
    {
      "status": 0,
      "user_id": 11,
      "user_name": "破解"
    },
    {
      "status": 0,
      "user_id": 12,
      "user_name": "敏捷"
    },
    {
      "status": 0,
      "user_id": 13,
      "user_name": "核桃仁"
    },
    {
      "status": 0,
      "user_id": 14,
      "user_name": "金木研"
    },
    {
      "status": 1,
      "user_id": 15,
      "user_name": "你要"
    },
    {
      "status": 0,
      "user_id": 16,
      "user_name": "月兔"
    },
    {
      "status": 0,
      "user_id": 17,
      "user_name": "办公费"
    },
    {
      "status": 1,
      "user_id": 18,
      "user_name": "阿尔"
    },
    {
      "status": 1,
      "user_id": 19,
      "user_name": "㘝惹我"
    },
    {
      "status": 0,
      "user_id": 20,
      "user_name": "王企鹅号"
    }
  ]
}